datavita/__init__.py
datavita/core/__init__.py
datavita/core/common/__init__.py
datavita/core/common/auth.py
datavita/core/common/contants.py
datavita/core/exc/__init__.py
datavita/core/exc/exception.py
datavita/core/schema/__init__.py
datavita/core/schema/apischema.py
datavita/core/schema/baseschema.py
datavita/core/transport/__init__.py
datavita/core/transport/apitransport.py
datavita/core/transport/comtransport.py
datavita/core/utils/__init__.py
datavita/core/utils/log.py
datavita/core/utils/param_generate.py
datavita/dpms/__init__.py
datavita/dpms/dpms_apis.py
datavita/dpms/dpms_data.py
datavita_dpms_python_sdk-0.0.1.dist-info/LICENSE
datavita_dpms_python_sdk-0.0.1.dist-info/METADATA
datavita_dpms_python_sdk-0.0.1.dist-info/WHEEL
datavita_dpms_python_sdk-0.0.1.dist-info/top_level.txt
datavita_dpms_python_sdk-0.0.1.dist-info/RECORD
