Metadata-Version: 2.1
Name: datavita-dpms-python-sdk
Version: 0.0.1
Summary: DataVita DPMS Python SDK
Home-page: https://www.datavita.com.cn
License: UNKNOWN
Platform: UNKNOWN
Classifier: Programming Language :: Python :: 3
Classifier: License :: OSI Approved :: MIT License
Classifier: Operating System :: OS Independent
Requires-Python: >=3.7
License-File: LICENSE
Requires-Dist: requests (>=2.25.1)
Requires-Dist: numpy (>=1.19.2)
Requires-Dist: pandas (>=1.1.3)
